deepvission/__init__.py
deepvission/vision.py
deepvission_nightly-1.0.1.dist-info/LICENSE
deepvission_nightly-1.0.1.dist-info/METADATA
deepvission_nightly-1.0.1.dist-info/WHEEL
deepvission_nightly-1.0.1.dist-info/top_level.txt
deepvission_nightly-1.0.1.dist-info/RECORD
