Metadata-Version: 2.1
Name: deepvission-nightly
Version: 1.0.1
Summary: Python package for Deep Neural Netrwork Pre-trained Model testing.
Home-page: https://github.com/suvhradipghosh07/deepvision
Author: Suvhradip Ghosh
Author-email: suvhradip.ai@gmail.com
License: MIT
Platform: UNKNOWN
Classifier: License :: OSI Approved :: MIT License
Classifier: Programming Language :: Python :: 3
Classifier: Programming Language :: Python :: 3.7
Requires-Dist: requests
Requires-Dist: keras
Requires-Dist: tensorflow
Requires-Dist: opencv-python
Requires-Dist: Pillow
Requires-Dist: numpy
